examples/__init__.py
examples/example_recording.py
examples/example_selection.py
examples/example_validation.py
examples/minimal_steamvr.py
tests/__init__.py
tests/test_data.py
tests/test_experiment.py
tests/test_recorder.py
tests/test_replay.py
vexptoolbox/__init__.py
vexptoolbox/data.py
vexptoolbox/experiment.py
vexptoolbox/eyeball.py
vexptoolbox/recorder.py
vexptoolbox/replay.py
vexptoolbox/stats.py
vexptoolbox/steamvr_debug.py
vexptoolbox/vrutil.py
vexptoolbox/models/unit_eye.gltf
vexptoolbox-0.1.2.dist-info/LICENSE
vexptoolbox-0.1.2.dist-info/METADATA
vexptoolbox-0.1.2.dist-info/WHEEL
vexptoolbox-0.1.2.dist-info/top_level.txt
vexptoolbox-0.1.2.dist-info/zip-safe
vexptoolbox-0.1.2.dist-info/RECORD
