Metadata-Version: 2.1
Name: vexptoolbox
Version: 0.1.2
Summary: Toolbox for Behavioral Experiments using Vizard
Home-page: https://github.com/ischtz/vizard-experiment-toolbox
Author: Immo Schuetz
Author-email: schuetz.immo@gmail.com
License: MIT
Classifier: License :: OSI Approved :: MIT License
Classifier: Intended Audience :: Science/Research
Classifier: Operating System :: OS Independent
Classifier: Programming Language :: Python :: 3
Classifier: Programming Language :: Python :: 2.7
License-File: LICENSE
